zinnia/__init__.py
zinnia/models/__init__.py
django_blog_zinnia_namespace-0.0.0.dist-info/METADATA
django_blog_zinnia_namespace-0.0.0.dist-info/WHEEL
django_blog_zinnia_namespace-0.0.0.dist-info/top_level.txt
django_blog_zinnia_namespace-0.0.0.dist-info/RECORD
