Metadata-Version: 2.1
Name: django-blog-zinnia-namespace
Version: 0.0.0
Summary: django-blog-zinnia-namespace
Home-page: UNKNOWN
Author: wTayyeb
Author-email: wtayyeb+django-blog-zinnia-namespace@gmail.com
License: MIT
Platform: UNKNOWN
Requires-Dist: django-blog-zinnia
